indra/__init__.py
indra/__main__.py
indra/cli.py
indra/emails.py
indra/fetch/__init__.py
indra/fetch/cds.py
indra/fetch/ecpds.py
indra/fetch/imd.py
indra/io/__init__.py
indra/io/download.py
indra/io/upload.py
indra/logging_config.py
indrastack-0.1.1.dist-info/LICENSE
indrastack-0.1.1.dist-info/METADATA
indrastack-0.1.1.dist-info/WHEEL
indrastack-0.1.1.dist-info/entry_points.txt
indrastack-0.1.1.dist-info/RECORD
