Metadata-Version: 2.3
Name: indrastack
Version: 0.1.1
Summary: 
License: GPL-3.0-or-later
Author: Sai Sneha
Author-email: sneha@artpark.in
Requires-Python: >=3.11,<4.0
Classifier: License :: OSI Approved :: GNU General Public License v3 or later (GPLv3+)
Classifier: Programming Language :: Python :: 3
Classifier: Programming Language :: Python :: 3.11
Classifier: Programming Language :: Python :: 3.12
Classifier: Programming Language :: Python :: 3.13
Requires-Dist: beautifulsoup4 (>=4.13.3,<5.0.0)
Requires-Dist: boto3 (>=1.37.18,<2.0.0)
Requires-Dist: cdsapi (>=0.7.5,<0.8.0)
Requires-Dist: geopandas (>=1.0.1,<2.0.0)
Requires-Dist: joblib (>=1.4.2,<2.0.0)
Requires-Dist: netcdf4 (>=1.7.2,<2.0.0)
Requires-Dist: pandas (>=2.2.3,<3.0.0)
Requires-Dist: python-dotenv (>=1.0.1,<2.0.0)
Requires-Dist: pyyaml (>=6.0.2,<7.0.0)
Requires-Dist: scipy (>=1.15.2,<2.0.0)
Requires-Dist: typer (>=0.15.2,<0.16.0)
